LICENSE
MANIFEST.in
README.md
setup.py
qlogs.egg-info/PKG-INFO
qlogs.egg-info/SOURCES.txt
qlogs.egg-info/dependency_links.txt
qlogs.egg-info/entry_points.txt
qlogs.egg-info/top_level.txt
src/__init__.py
src/qlogs.py
src/data/cve-2017-9841.json
src/data/cve-2018-15133.json