Metadata-Version: 2.1
Name: qlogs
Version: 0.0.7
Summary: A package for querying log files for evidence of compromise.
Home-page: https://github.com/chrisdunne/qlogs
Author: Chris Dunne
Author-email: contact@chrisdunne.net
Classifier: Programming Language :: Python :: 3
Classifier: License :: OSI Approved :: MIT License
Classifier: Operating System :: OS Independent
License-File: LICENSE
